LICENSE
MANIFEST.in
README.rst
setup.cfg
setup.py
phone_email_auth/__init__.py
phone_email_auth/admin.py
phone_email_auth/apps.py
phone_email_auth/models.py
phone_email_auth/tests.py
phone_email_auth/urls.py
phone_email_auth/utils.py
phone_email_auth/views.py
phone_email_auth.egg-info/PKG-INFO
phone_email_auth.egg-info/SOURCES.txt
phone_email_auth.egg-info/dependency_links.txt
phone_email_auth.egg-info/requires.txt
phone_email_auth.egg-info/top_level.txt
phone_email_auth/migrations/__init__.py