Metadata-Version: 2.1
Name: phone_email_auth
Version: 0.11
Summary: A Django app to use services of phone.email.
Home-page: https://www.phone.email/
Author: Phone Email
Author-email: mg@phone.email
License: BSD-3-Clause
Classifier: Environment :: Web Environment
Classifier: Framework :: Django
Classifier: Intended Audience :: Developers
Classifier: License :: OSI Approved :: BSD License
Classifier: Programming Language :: Python :: 3 :: Only
License-File: LICENSE
Requires-Dist: requests
